.gitignore
.travis.yml
CHANGELOG.rst
LICENSE-MIT
MANIFEST.in
README.rst
requirements-dev.txt
requirements.txt
setup.py
test.sh
resolve_link/__init__.py
resolve_link/__init__.pyc
resolve_link.egg-info/PKG-INFO
resolve_link.egg-info/SOURCES.txt
resolve_link.egg-info/dependency_links.txt
resolve_link.egg-info/pbr.json
resolve_link.egg-info/top_level.txt
resolve_link/test/__init__.py
resolve_link/test/__init__.pyc
resolve_link/test/test.py
resolve_link/test/test.pyc