Metadata-Version: 1.1
Name: resolve_link
Version: 1.2.0
Summary: Resolve complete/partial URLs against a canonical target URL
Home-page: https://github.com/underdogio/python-resolve-link
Author: Todd Wolfson
Author-email: todd@twolfson.com
License: MIT
Download-URL: https://github.com/underdogio/python-resolve-link/archive/master.zip
Keywords: resolve,link,url,target,canonical
Platform: UNKNOWN
Classifier: Development Status :: 4 - Beta
Classifier: Intended Audience :: Developers
Classifier: License :: OSI Approved :: MIT License
Classifier: Operating System :: OS Independent
Classifier: Programming Language :: Python
Classifier: Topic :: Internet :: WWW/HTTP
